setup.cfg
setup.py
makerestapiclient/__init__.py
makerestapiclient/__main__.py
makerestapiclient/http.py
makerestapiclient/makerestapiclient.py
makerestapiclient.egg-info/PKG-INFO
makerestapiclient.egg-info/SOURCES.txt
makerestapiclient.egg-info/dependency_links.txt
makerestapiclient.egg-info/entry_points.txt
makerestapiclient.egg-info/requires.txt
makerestapiclient.egg-info/top_level.txt
makerestapiclient/templates/arglist.mustache
makerestapiclient/templates/dict.mustache
makerestapiclient/templates/endpoint.mustache
makerestapiclient/templates/head.mustache