Metadata-Version: 1.1
Name: makerestapiclient
Version: 2.0.3
Summary: Simple python utility to build a python client class for interfacing with a REST API
Home-page: https://github.com/Taywee/makerestapiclient
Author: Taylor C. Richberger <tcr@absolute-performance.com>
Author-email: tcr@absolute-performance.com
License: MIT
Download-URL: https://github.com/Taywee/makerestapiclient
Keywords: python http rest management
Platform: UNKNOWN
Classifier: Intended Audience :: Developers
Classifier: License :: OSI Approved :: MIT License
Classifier: Natural Language :: English
Classifier: Programming Language :: Python
Classifier: Programming Language :: Python :: 2
Classifier: Programming Language :: Python :: 2.7
Classifier: Programming Language :: Python :: 3
Classifier: Programming Language :: Python :: 3.5
Classifier: Topic :: Internet :: WWW/HTTP
Classifier: Topic :: Software Development :: Libraries :: Python Modules
